{
  "route": {
    "latMax": "37.79314",
    "stop": [
      {
        "lon": "-122.39753",
        "title": "Davis St & Pine St",
        "stopId": "14347",
        "tag": "4347",
        "lat": "37.7926099"
      },
      {
        "lon": "-122.4025399",
        "title": "Pine St & Montgomery St",
        "stopId": "15944",
        "tag": "5944",
        "lat": "37.79194"
      },
      {
        "lon": "-122.4459299",
        "title": "Presidio Ave & Geary Blvd",
        "stopId": "16093",
        "tag": "6093",
        "lat": "37.7826699"
      },
      {
        "lon": "-122.44757",
        "title": "Masonic Ave & Geary Blvd",
        "stopId": "15710",
        "tag": "5710",
        "lat": "37.7821399"
      },
      {
        "lon": "-122.44721",
        "title": "Turk St & Masonic Ave",
        "stopId": "16724",
        "tag": "6724",
        "lat": "37.7786599"
      },
      {
        "lon": "-122.44966",
        "title": "Turk St & Roselyn Ter",
        "stopId": "16730",
        "tag": "6730",
        "lat": "37.7783499"
      },
      {
        "lon": "-122.4517",
        "title": "Turk St & Chabot Ter",
        "stopId": "16714",
        "tag": "6714",
        "lat": "37.7780899"
      },
      {
        "lon": "-122.45328",
        "title": "Turk St & Parker Ave",
        "stopId": "16727",
        "tag": "6727",
        "lat": "37.7779099"
      },
      {
        "lon": "-122.45537",
        "title": "Turk St & Stanyan St",
        "stopId": "16731",
        "tag": "6731",
        "lat": "37.7776399"
      },
      {
        "lon": "-122.4588599",
        "title": "Balboa St & Arguello Blvd",
        "stopId": "13067",
        "tag": "3067",
        "lat": "37.7774699"
      },
      {
        "lon": "-122.4617499",
        "title": "Balboa St & 4th Ave",
        "stopId": "13032",
        "tag": "3032",
        "lat": "37.7774"
      },
      {
        "lon": "-122.4641599",
        "title": "Balboa St & 6th Ave",
        "stopId": "13034",
        "tag": "3034",
        "lat": "37.77729"
      },
      {
        "lon": "-122.4660399",
        "title": "Balboa St & 8th Ave",
        "stopId": "13036",
        "tag": "3036",
        "lat": "37.7772"
      },
      {
        "lon": "-122.4681699",
        "title": "Balboa St & 10th Ave",
        "stopId": "13038",
        "tag": "3038",
        "lat": "37.7771"
      },
      {
        "lon": "-122.4703099",
        "title": "Balboa St & 12th Ave",
        "stopId": "13040",
        "tag": "3040",
        "lat": "37.777"
      },
      {
        "lon": "-122.47192",
        "title": "Balboa St & Park Presidio Blvd",
        "stopId": "17696",
        "tag": "7696",
        "lat": "37.7768999"
      },
      {
        "lon": "-122.47053",
        "title": "Balboa St & 12th Ave",
        "stopId": "13041",
        "tag": "3041",
        "lat": "37.7768699"
      },
      {
        "lon": "-122.4683899",
        "title": "Balboa St & 10th Ave",
        "stopId": "13039",
        "tag": "3039",
        "lat": "37.77697"
      },
      {
        "lon": "-122.4662599",
        "title": "Balboa St & 8th Ave",
        "stopId": "13037",
        "tag": "3037",
        "lat": "37.77707"
      },
      {
        "lon": "-122.46385",
        "title": "Balboa St & 6th Ave",
        "stopId": "13035",
        "tag": "3035",
        "lat": "37.7771699"
      },
      {
        "lon": "-122.46197",
        "title": "Balboa St & 4th Ave",
        "stopId": "13033",
        "tag": "3033",
        "lat": "37.7772599"
      },
      {
        "lon": "-122.4581799",
        "title": "Turk St & Arguello Blvd",
        "stopId": "16709",
        "tag": "6709",
        "lat": "37.77715"
      },
      {
        "lon": "-122.45503",
        "title": "Turk St & Stanyan St",
        "stopId": "16732",
        "tag": "6732",
        "lat": "37.7775599"
      },
      {
        "lon": "-122.45348",
        "title": "Turk St & Parker Ave",
        "stopId": "16728",
        "tag": "6728",
        "lat": "37.7777499"
      },
      {
        "lon": "-122.45137",
        "title": "Turk St & Chabot Ter",
        "stopId": "16715",
        "tag": "6715",
        "lat": "37.7780099"
      },
      {
        "lon": "-122.44959",
        "title": "Turk St & Roselyn Ter",
        "stopId": "16729",
        "tag": "6729",
        "lat": "37.7782399"
      },
      {
        "lon": "-122.447",
        "title": "Masonic Ave & Turk St",
        "stopId": "15718",
        "tag": "5718",
        "lat": "37.77877"
      },
      {
        "lon": "-122.44728",
        "title": "Masonic Ave & Geary Blvd",
        "stopId": "15709",
        "tag": "5709",
        "lat": "37.7821299"
      },
      {
        "lon": "-122.4458",
        "title": "Presidio Ave & Geary Blvd",
        "stopId": "16092",
        "tag": "6092",
        "lat": "37.7827099"
      },
      {
        "lon": "-122.4009499",
        "title": "Bush St & Sansome St",
        "stopId": "17302",
        "tag": "7302",
        "lat": "37.79107"
      },
      {
        "lon": "-122.4008599",
        "title": "Sansome St & Pine St",
        "stopId": "16332",
        "tag": "6332",
        "lat": "37.7920199"
      },
      {
        "lon": "-122.39987",
        "title": "California St & Battery St",
        "stopId": "13851",
        "tag": "3851",
        "lat": "37.79314"
      },
      {
        "lon": "-122.39753",
        "title": "Davis St & Pine St",
        "stopId": "134347",
        "tag": "34347",
        "lat": "37.7926099"
      }
    ],
    "title": "31BX-Balboa B Express",
    "lonMin": "-122.47192",
    "color": "cc3333",
    "direction": [
      {
        "stop": [
          {
            "tag": "4347"
          },
          {
            "tag": "5944"
          },
          {
            "tag": "6093"
          },
          {
            "tag": "5710"
          },
          {
            "tag": "6724"
          },
          {
            "tag": "6730"
          },
          {
            "tag": "6714"
          },
          {
            "tag": "6727"
          },
          {
            "tag": "6731"
          },
          {
            "tag": "3067"
          },
          {
            "tag": "3032"
          },
          {
            "tag": "3034"
          },
          {
            "tag": "3036"
          },
          {
            "tag": "3038"
          },
          {
            "tag": "3040"
          },
          {
            "tag": "7696"
          }
        ],
        "title": "Outbound to Park Presidio Boulevard",
        "useForUI": "true",
        "tag": "31BX_O_F00",
        "name": "Outbound"
      },
      {
        "stop": [
          {
            "tag": "3041"
          },
          {
            "tag": "3039"
          },
          {
            "tag": "3037"
          },
          {
            "tag": "3035"
          },
          {
            "tag": "3033"
          },
          {
            "tag": "6709"
          },
          {
            "tag": "6732"
          },
          {
            "tag": "6728"
          },
          {
            "tag": "6715"
          },
          {
            "tag": "6729"
          },
          {
            "tag": "5718"
          },
          {
            "tag": "5709"
          },
          {
            "tag": "6092"
          },
          {
            "tag": "7302"
          },
          {
            "tag": "6332"
          },
          {
            "tag": "3851"
          },
          {
            "tag": "34347"
          }
        ],
        "title": "Inbound to Financial District",
        "useForUI": "true",
        "tag": "31BX_I_F00",
        "name": "Inbound"
      }
    ],
    "tag": "31BX",
    "path": [
      {
        "point": [
          {
            "lon": "-122.4458",
            "lat": "37.78271"
          },
          {
            "lon": "-122.44605",
            "lat": "37.78351"
          },
          {
            "lon": "-122.44643",
            "lat": "37.78538"
          },
          {
            "lon": "-122.40095",
            "lat": "37.79107"
          },
          {
            "lon": "-122.40076",
            "lat": "37.79118"
          },
          {
            "lon": "-122.40086",
            "lat": "37.79202"
          },
          {
            "lon": "-122.40114",
            "lat": "37.79307"
          },
          {
            "lon": "-122.39997",
            "lat": "37.79321"
          },
          {
            "lon": "-122.39987",
            "lat": "37.79314"
          },
          {
            "lon": "-122.39762",
            "lat": "37.79351"
          },
          {
            "lon": "-122.39753",
            "lat": "37.79261"
          }
        ]
      },
      {
        "point": [
          {
            "lon": "-122.47053",
            "lat": "37.77687"
          },
          {
            "lon": "-122.46839",
            "lat": "37.77697"
          },
          {
            "lon": "-122.46626",
            "lat": "37.77707"
          },
          {
            "lon": "-122.46385",
            "lat": "37.77717"
          },
          {
            "lon": "-122.46197",
            "lat": "37.77726"
          },
          {
            "lon": "-122.45901",
            "lat": "37.77747"
          },
          {
            "lon": "-122.45835",
            "lat": "37.77722"
          },
          {
            "lon": "-122.45818",
            "lat": "37.77715"
          },
          {
            "lon": "-122.45503",
            "lat": "37.77756"
          },
          {
            "lon": "-122.45348",
            "lat": "37.77775"
          },
          {
            "lon": "-122.45137",
            "lat": "37.77801"
          },
          {
            "lon": "-122.44959",
            "lat": "37.7782399"
          },
          {
            "lon": "-122.44705",
            "lat": "37.77863"
          },
          {
            "lon": "-122.447",
            "lat": "37.77877"
          },
          {
            "lon": "-122.44762",
            "lat": "37.78151"
          },
          {
            "lon": "-122.44728",
            "lat": "37.78213"
          },
          {
            "lon": "-122.44731",
            "lat": "37.7824"
          },
          {
            "lon": "-122.44591",
            "lat": "37.7824"
          },
          {
            "lon": "-122.4458",
            "lat": "37.78271"
          }
        ]
      },
      {
        "point": [
          {
            "lon": "-122.39753",
            "lat": "37.79261"
          },
          {
            "lon": "-122.40254",
            "lat": "37.7919399"
          },
          {
            "lon": "-122.44662",
            "lat": "37.78631"
          },
          {
            "lon": "-122.44593",
            "lat": "37.78267"
          },
          {
            "lon": "-122.44583",
            "lat": "37.78249"
          },
          {
            "lon": "-122.44731",
            "lat": "37.7824"
          },
          {
            "lon": "-122.44757",
            "lat": "37.78214"
          },
          {
            "lon": "-122.44762",
            "lat": "37.78151"
          },
          {
            "lon": "-122.44705",
            "lat": "37.77863"
          },
          {
            "lon": "-122.44721",
            "lat": "37.77866"
          },
          {
            "lon": "-122.44966",
            "lat": "37.77835"
          },
          {
            "lon": "-122.4517",
            "lat": "37.77809"
          },
          {
            "lon": "-122.45328",
            "lat": "37.77791"
          },
          {
            "lon": "-122.45537",
            "lat": "37.77764"
          },
          {
            "lon": "-122.45835",
            "lat": "37.77722"
          },
          {
            "lon": "-122.45886",
            "lat": "37.77747"
          },
          {
            "lon": "-122.45901",
            "lat": "37.77747"
          },
          {
            "lon": "-122.46175",
            "lat": "37.7774"
          },
          {
            "lon": "-122.46416",
            "lat": "37.77729"
          },
          {
            "lon": "-122.46604",
            "lat": "37.7772"
          },
          {
            "lon": "-122.46817",
            "lat": "37.7771"
          },
          {
            "lon": "-122.47031",
            "lat": "37.777"
          },
          {
            "lon": "-122.47192",
            "lat": "37.7769"
          }
        ]
      }
    ],
    "lonMax": "-122.39753",
    "oppositeColor": "ffffff",
    "latMin": "37.7768699"
  },
  "copyright": "All data copyright San Francisco Muni 2017."
}